clean_data.py
cluster.py
process.py
setup.py
JDRA.egg-info/PKG-INFO
JDRA.egg-info/SOURCES.txt
JDRA.egg-info/dependency_links.txt
JDRA.egg-info/top_level.txt