Metadata-Version: 1.0
Name: JDRA
Version: 0.0.1
Summary: JD robot-adivisor,Combining the machine learning method with the behaviour finance theory to cluster customers based on the attention list of stocks in chinese market
Home-page: UNKNOWN
Author: Jiacheng Liu
Author-email: Kevin_ljc@foxmail.com
License: UNKNOWN
Platform: UNKNOWN
